setup.cfg
setup.py
subnetting/__init__.py
subnetting/subnetting.py
subnetting.egg-info/PKG-INFO
subnetting.egg-info/SOURCES.txt
subnetting.egg-info/dependency_links.txt
subnetting.egg-info/entry_points.txt
subnetting.egg-info/top_level.txt