Metadata-Version: 1.1
Name: subnetting
Version: 0.0.3
Summary: IPv4 subnetting calculator CLI
Home-page: https://github.com/thimoonxy/subnetting
Author: Simon Xie
Author-email: thimoon@sina.com
License: MIT
Download-URL: https://github.com/thimoonxy/subnetting/tarball/0.0.3
Keywords: subnetting,CIDR,calculating,network,troubleshooting
Platform: UNKNOWN
Classifier: Development Status :: 3 - Alpha
Classifier: Intended Audience :: Developers
Classifier: Intended Audience :: System Administrators
Classifier: Topic :: System :: Networking
Classifier: License :: OSI Approved :: MIT License
Classifier: Programming Language :: Python :: 2
Classifier: Programming Language :: Python :: 2.6
Classifier: Programming Language :: Python :: 2.7
Classifier: Programming Language :: Python :: 3
Classifier: Programming Language :: Python :: 3.3
Classifier: Programming Language :: Python :: 3.4
Classifier: Programming Language :: Python :: 3.5
